{"Valgart":"Folketingsvalg","Valgdag":"24-03-2026","FrigivelsesTidspunktUTC":"24-03-2026 17:23:46","Kommune":"Tønder","Kommunekode":550,"Afstemningsområde":"Brøns","AfstemningsområdeDagiId":"711078","AfstemningsområdeNummer":24,"Valgdeltagelse":[{"AntalStemmeberretigedeVælgere":669,"AfgivneStemmer":53,"Tidspunkt":"09:00:00"},{"AntalStemmeberretigedeVælgere":669,"AfgivneStemmer":168,"Tidspunkt":"11:30:00"},{"AntalStemmeberretigedeVælgere":669,"AfgivneStemmer":282,"Tidspunkt":"15:00:00"},{"AntalStemmeberretigedeVælgere":669,"AfgivneStemmer":490,"Tidspunkt":"18:00:00"}]}