{"Valgart":"Folketingsvalg","Valgdag":"24-03-2026","FrigivelsesTidspunktUTC":"24-03-2026 19:10:16","Kommune":"Odsherred","Kommunekode":306,"Afstemningsområde":"Lumsås","AfstemningsområdeDagiId":"701326","AfstemningsområdeNummer":12,"Valgdeltagelse":[{"AntalStemmeberretigedeVælgere":516,"AfgivneStemmer":63,"Tidspunkt":"09:02:00"},{"AntalStemmeberretigedeVælgere":516,"AfgivneStemmer":99,"Tidspunkt":"10:01:00"},{"AntalStemmeberretigedeVælgere":516,"AfgivneStemmer":132,"Tidspunkt":"11:01:00"},{"AntalStemmeberretigedeVælgere":516,"AfgivneStemmer":164,"Tidspunkt":"12:00:00"},{"AntalStemmeberretigedeVælgere":516,"AfgivneStemmer":193,"Tidspunkt":"13:01:00"},{"AntalStemmeberretigedeVælgere":516,"AfgivneStemmer":218,"Tidspunkt":"14:00:00"},{"AntalStemmeberretigedeVælgere":516,"AfgivneStemmer":258,"Tidspunkt":"15:00:00"},{"AntalStemmeberretigedeVælgere":516,"AfgivneStemmer":302,"Tidspunkt":"16:01:00"},{"AntalStemmeberretigedeVælgere":516,"AfgivneStemmer":343,"Tidspunkt":"17:00:00"},{"AntalStemmeberretigedeVælgere":516,"AfgivneStemmer":385,"Tidspunkt":"18:00:00"},{"AntalStemmeberretigedeVælgere":516,"AfgivneStemmer":410,"Tidspunkt":"19:06:00"},{"AntalStemmeberretigedeVælgere":516,"AfgivneStemmer":427,"Tidspunkt":"20:00:00"}]}