{"Valgart":"Folketingsvalg","Valgdag":"24-03-2026","FrigivelsesTidspunktUTC":"24-03-2026 19:09:45","Kommune":"Hedensted","Kommunekode":766,"Afstemningsområde":"Rask Mølle","AfstemningsområdeDagiId":"703900","AfstemningsområdeNummer":17,"Valgdeltagelse":[{"AntalStemmeberretigedeVælgere":1099,"AfgivneStemmer":81,"Tidspunkt":"09:00:00"},{"AntalStemmeberretigedeVælgere":1099,"AfgivneStemmer":247,"Tidspunkt":"12:00:00"},{"AntalStemmeberretigedeVælgere":1099,"AfgivneStemmer":696,"Tidspunkt":"17:00:00"},{"AntalStemmeberretigedeVælgere":1099,"AfgivneStemmer":945,"Tidspunkt":"20:00:00"}]}