{"Valgart":"Folketingsvalg","Valgdag":"24-03-2026","FrigivelsesTidspunktUTC":"24-03-2026 19:03:30","Kommune":"Slagelse","Kommunekode":330,"Afstemningsområde":"Dalmose - Dalmosehallen","AfstemningsområdeDagiId":"705710","AfstemningsområdeNummer":10,"Valgdeltagelse":[{"AntalStemmeberretigedeVælgere":2408,"AfgivneStemmer":572,"Tidspunkt":"12:00:00"},{"AntalStemmeberretigedeVælgere":2408,"AfgivneStemmer":758,"Tidspunkt":"14:00:00"},{"AntalStemmeberretigedeVælgere":2408,"AfgivneStemmer":1118,"Tidspunkt":"16:00:00"},{"AntalStemmeberretigedeVælgere":2408,"AfgivneStemmer":1688,"Tidspunkt":"18:00:00"},{"AntalStemmeberretigedeVælgere":2408,"AfgivneStemmer":1960,"Tidspunkt":"20:00:00"}]}