{"Valgart":"Folketingsvalg","Valgdag":"24-03-2026","FrigivelsesTidspunktUTC":"24-03-2026 19:13:28","Kommune":"Roskilde","Kommunekode":265,"Afstemningsområde":"Tjørnegård","AfstemningsområdeDagiId":"711710","AfstemningsområdeNummer":10,"Valgdeltagelse":[{"AntalStemmeberretigedeVælgere":5417,"AfgivneStemmer":914,"Tidspunkt":"09:00:00"},{"AntalStemmeberretigedeVælgere":5417,"AfgivneStemmer":1354,"Tidspunkt":"11:00:00"},{"AntalStemmeberretigedeVælgere":5417,"AfgivneStemmer":1813,"Tidspunkt":"13:00:00"},{"AntalStemmeberretigedeVælgere":5417,"AfgivneStemmer":2276,"Tidspunkt":"15:00:00"},{"AntalStemmeberretigedeVælgere":5417,"AfgivneStemmer":3085,"Tidspunkt":"17:00:00"},{"AntalStemmeberretigedeVælgere":5417,"AfgivneStemmer":3870,"Tidspunkt":"19:00:00"},{"AntalStemmeberretigedeVælgere":5417,"AfgivneStemmer":4094,"Tidspunkt":"20:00:00"}]}