{"Valgart":"Folketingsvalg","Valgdag":"24-03-2026","FrigivelsesTidspunktUTC":"24-03-2026 19:01:42","Kommune":"Ringkøbing-Skjern","Kommunekode":760,"Afstemningsområde":"Ådum","AfstemningsområdeDagiId":"748670","AfstemningsområdeNummer":4,"Valgdeltagelse":[{"AntalStemmeberretigedeVælgere":765,"AfgivneStemmer":30,"Tidspunkt":"08:00:00"},{"AntalStemmeberretigedeVælgere":765,"AfgivneStemmer":72,"Tidspunkt":"09:00:00"},{"AntalStemmeberretigedeVælgere":765,"AfgivneStemmer":108,"Tidspunkt":"10:00:00"},{"AntalStemmeberretigedeVælgere":765,"AfgivneStemmer":148,"Tidspunkt":"11:00:00"},{"AntalStemmeberretigedeVælgere":765,"AfgivneStemmer":186,"Tidspunkt":"12:00:00"},{"AntalStemmeberretigedeVælgere":765,"AfgivneStemmer":212,"Tidspunkt":"13:00:00"},{"AntalStemmeberretigedeVælgere":765,"AfgivneStemmer":247,"Tidspunkt":"14:00:00"},{"AntalStemmeberretigedeVælgere":765,"AfgivneStemmer":277,"Tidspunkt":"15:00:00"},{"AntalStemmeberretigedeVælgere":765,"AfgivneStemmer":317,"Tidspunkt":"16:00:00"},{"AntalStemmeberretigedeVælgere":765,"AfgivneStemmer":416,"Tidspunkt":"17:00:00"},{"AntalStemmeberretigedeVælgere":765,"AfgivneStemmer":503,"Tidspunkt":"18:00:00"},{"AntalStemmeberretigedeVælgere":765,"AfgivneStemmer":567,"Tidspunkt":"19:00:00"},{"AntalStemmeberretigedeVælgere":765,"AfgivneStemmer":615,"Tidspunkt":"20:00:00"}]}